python_ntfy/__init__.py
python_ntfy/_exceptions.py
python_ntfy/_get_functions.py
python_ntfy/_ntfy.py
python_ntfy/_send_functions.py
python_ntfy/client.py
python_ntfy/py.typed
python_ntfy-0.10.1.dist-info/WHEEL
python_ntfy-0.10.1.dist-info/METADATA
python_ntfy-0.10.1.dist-info/RECORD
