Metadata-Version: 2.4
Name: python-ntfy
Version: 0.10.1
Summary: An easy-to-use library for the ntfy notification service.
Keywords: ntfy,notifications,push,http,api
Author: Matthew Cane
Author-email: Matthew Cane <matthew.cane0@gmail.com>
License-Expression: MIT
Classifier: Development Status :: 4 - Beta
Classifier: Intended Audience :: Developers
Classifier: License :: OSI Approved :: MIT License
Classifier: Operating System :: OS Independent
Classifier: Programming Language :: Python :: 3
Classifier: Programming Language :: Python :: 3.10
Classifier: Programming Language :: Python :: 3.11
Classifier: Programming Language :: Python :: 3.12
Classifier: Programming Language :: Python :: 3.13
Classifier: Programming Language :: Python :: 3.14
Classifier: Topic :: Communications
Classifier: Topic :: Internet :: WWW/HTTP
Classifier: Topic :: Software Development :: Libraries :: Python Modules
Requires-Dist: requests>=2.31.0
Requires-Python: >=3.10
Project-URL: Changelog, https://github.com/matthewcane/python-ntfy/releases
Project-URL: Documentation, https://matthewcane.github.io/python-ntfy/
Project-URL: Homepage, https://github.com/matthewcane/python-ntfy
Project-URL: Issues, https://github.com/matthewcane/python-ntfy/issues
Project-URL: Repository, https://github.com/matthewcane/python-ntfy
